jirafs_mermaid/__init__.py
jirafs_mermaid/plugin.py
jirafs_mermaid-1.0.2.dist-info/METADATA
jirafs_mermaid-1.0.2.dist-info/WHEEL
jirafs_mermaid-1.0.2.dist-info/entry_points.txt
jirafs_mermaid-1.0.2.dist-info/top_level.txt
jirafs_mermaid-1.0.2.dist-info/RECORD
