Metadata-Version: 2.1
Name: jirafs-mermaid
Version: 1.0.2
Summary: Automatically include diagrams and charts generated with mermaid in your Jira issues.
Home-page: https://github.com/coddingtonbear/jirafs-mermaid
Author: Adam Coddington
Author-email: me@adamcoddington.net
License: UNKNOWN
Platform: UNKNOWN
Classifier: License :: OSI Approved :: MIT License
Classifier: Operating System :: OS Independent
Classifier: Programming Language :: Python :: 3
